riptr.py
riptr-1.2.2.dist-info/METADATA
riptr-1.2.2.dist-info/RECORD
riptr-1.2.2.dist-info/WHEEL
riptr-1.2.2.dist-info/entry_points.txt
riptr-1.2.2.dist-info/top_level.txt
