Metadata-Version: 2.1
Name: riptr
Version: 1.2.2
Summary: Replacement for tr/sed replace in python
Home-page: https://github.com/noahp/python-riptr
Author: Noah Pendleton
Author-email: 2538614+noahp@users.noreply.github.com
License: UNKNOWN
Platform: UNKNOWN
